model_equality_testing/__init__.py
model_equality_testing/algorithm.py
model_equality_testing/dataset.py
model_equality_testing/distribution.py
model_equality_testing/pvalue.py
model_equality_testing/tests.py
model_equality_testing/utils.py
model_equality_testing-0.0.2.dist-info/LICENSE
model_equality_testing-0.0.2.dist-info/METADATA
model_equality_testing-0.0.2.dist-info/WHEEL
model_equality_testing-0.0.2.dist-info/top_level.txt
model_equality_testing-0.0.2.dist-info/RECORD
