Metadata-Version: 2.1
Name: model-equality-testing
Version: 0.0.2
Summary: Package to conduct model equality testing for black-box language model APIs
Author-email: Irena Gao <irena@cs.stanford.edu>
Project-URL: Homepage, https://github.com/i-gao/model-equality-testing
Project-URL: Issues, https://github.com/i-gao/model-equality-testing/issues
Classifier: Programming Language :: Python :: 3
Classifier: License :: OSI Approved :: MIT License
Classifier: Operating System :: OS Independent
Requires-Python: >=3.10
License-File: LICENSE
Requires-Dist: numpy
Requires-Dist: torch
Requires-Dist: matplotlib
